azure/mgmt/lambdatesthyperexecute/__init__.py
azure/mgmt/lambdatesthyperexecute/_client.py
azure/mgmt/lambdatesthyperexecute/_configuration.py
azure/mgmt/lambdatesthyperexecute/_patch.py
azure/mgmt/lambdatesthyperexecute/_version.py
azure/mgmt/lambdatesthyperexecute/py.typed
azure/mgmt/lambdatesthyperexecute/_utils/__init__.py
azure/mgmt/lambdatesthyperexecute/_utils/model_base.py
azure/mgmt/lambdatesthyperexecute/_utils/serialization.py
azure/mgmt/lambdatesthyperexecute/aio/__init__.py
azure/mgmt/lambdatesthyperexecute/aio/_client.py
azure/mgmt/lambdatesthyperexecute/aio/_configuration.py
azure/mgmt/lambdatesthyperexecute/aio/_patch.py
azure/mgmt/lambdatesthyperexecute/aio/operations/__init__.py
azure/mgmt/lambdatesthyperexecute/aio/operations/_operations.py
azure/mgmt/lambdatesthyperexecute/aio/operations/_patch.py
azure/mgmt/lambdatesthyperexecute/models/__init__.py
azure/mgmt/lambdatesthyperexecute/models/_enums.py
azure/mgmt/lambdatesthyperexecute/models/_models.py
azure/mgmt/lambdatesthyperexecute/models/_patch.py
azure/mgmt/lambdatesthyperexecute/operations/__init__.py
azure/mgmt/lambdatesthyperexecute/operations/_operations.py
azure/mgmt/lambdatesthyperexecute/operations/_patch.py
azure_mgmt_lambdatesthyperexecute-1.0.0.dist-info/LICENSE
azure_mgmt_lambdatesthyperexecute-1.0.0.dist-info/METADATA
azure_mgmt_lambdatesthyperexecute-1.0.0.dist-info/WHEEL
azure_mgmt_lambdatesthyperexecute-1.0.0.dist-info/top_level.txt
azure_mgmt_lambdatesthyperexecute-1.0.0.dist-info/RECORD
